paccreator/__init__.py
paccreator/helpers.py
paccreator/paccreator.py
paccreator/paccreatorconfig.py
paccreator/template.js.jinja
paccreator-0.2.2.dist-info/LICENSE
paccreator-0.2.2.dist-info/METADATA
paccreator-0.2.2.dist-info/WHEEL
paccreator-0.2.2.dist-info/top_level.txt
paccreator-0.2.2.dist-info/RECORD
