Metadata-Version: 2.1
Name: paccreator
Version: 0.2.2
Summary: This package makes it possible to create simple proxy auto-config (PAC) files declaratively.
Author-email: Heiko Schmidt <73h@gmx.net>
Maintainer-email: Heiko Schmidt <73h@gmx.net>
License: MIT License
Project-URL: Homepage, https://github.com/73h/paccreator
Keywords: proxy auto-config,auto-config,pac,wpad,proxy,findproxyforurl
Classifier: Development Status :: 4 - Beta
Classifier: Programming Language :: Python :: 3
Classifier: Operating System :: OS Independent
Requires-Python: >=3.9
License-File: LICENSE
Requires-Dist: pyyaml
Requires-Dist: Jinja2
Provides-Extra: test
Requires-Dist: watching-testrunner ; extra == 'test'
Requires-Dist: pytest ; extra == 'test'
Requires-Dist: pytest-cov ; extra == 'test'
Requires-Dist: PyPAC ; extra == 'test'
